cupy/__init__.py
cupy/_environment.py
cupy/_util.cp37-win_amd64.pyd
cupy/_version.py
cupy/cublas.py
cupy/cudnn.cp37-win_amd64.pyd
cupy/cusolver.cp37-win_amd64.pyd
cupy/cusparse.py
cupy/cutensor.cp37-win_amd64.pyd
cupy/.data/_wheel.json
cupy/.data/lib/nvToolsExt64_1.dll
cupy/_binary/__init__.py
cupy/_binary/elementwise.py
cupy/_binary/packing.py
cupy/_core/__init__.py
cupy/_core/_accelerator.cp37-win_amd64.pyd
cupy/_core/_carray.cp37-win_amd64.pyd
cupy/_core/_codeblock.py
cupy/_core/_cub_reduction.cp37-win_amd64.pyd
cupy/_core/_dtype.cp37-win_amd64.pyd
cupy/_core/_fusion_interface.py
cupy/_core/_fusion_kernel.cp37-win_amd64.pyd
cupy/_core/_fusion_op.py
cupy/_core/_fusion_optimization.py
cupy/_core/_fusion_thread_local.cp37-win_amd64.pyd
cupy/_core/_fusion_trace.cp37-win_amd64.pyd
cupy/_core/_fusion_variable.cp37-win_amd64.pyd
cupy/_core/_gufuncs.py
cupy/_core/_kernel.cp37-win_amd64.pyd
cupy/_core/_memory_range.cp37-win_amd64.pyd
cupy/_core/_optimize_config.cp37-win_amd64.pyd
cupy/_core/_reduction.cp37-win_amd64.pyd
cupy/_core/_routines_binary.cp37-win_amd64.pyd
cupy/_core/_routines_indexing.cp37-win_amd64.pyd
cupy/_core/_routines_linalg.cp37-win_amd64.pyd
cupy/_core/_routines_logic.cp37-win_amd64.pyd
cupy/_core/_routines_manipulation.cp37-win_amd64.pyd
cupy/_core/_routines_math.cp37-win_amd64.pyd
cupy/_core/_routines_sorting.cp37-win_amd64.pyd
cupy/_core/_routines_statistics.cp37-win_amd64.pyd
cupy/_core/_scalar.cp37-win_amd64.pyd
cupy/_core/_ufuncs.py
cupy/_core/core.cp37-win_amd64.pyd
cupy/_core/dlpack.cp37-win_amd64.pyd
cupy/_core/flags.cp37-win_amd64.pyd
cupy/_core/fusion.cp37-win_amd64.pyd
cupy/_core/internal.cp37-win_amd64.pyd
cupy/_core/new_fusion.cp37-win_amd64.pyd
cupy/_core/raw.cp37-win_amd64.pyd
cupy/_core/syncdetect.py
cupy/_core/include/cupy/README.md
cupy/_core/include/cupy/atomics.cuh
cupy/_core/include/cupy/carray.cuh
cupy/_core/include/cupy/complex.cuh
cupy/_core/include/cupy/cuComplex_bridge.h
cupy/_core/include/cupy/hip_workaround.cuh
cupy_cuda114-10.6.0.dist-info/METADATA
cupy_cuda114-10.6.0.dist-info/WHEEL
cupy_cuda114-10.6.0.dist-info/license.rst
cupy_cuda114-10.6.0.dist-info/top_level.txt
cupy_cuda114-10.6.0.dist-info/RECORD
